{
  "label": "Layout",
  "comment": "Exported from virtual prairie",
  "children": [
    {
      "id": 0,
      "x": 118.374565,
      "z": 43.2301064,
      "tags": [
        "CWArm25",
        "CCWArm25"
      ]
    },
    {
      "id": 1,
      "x": -123.553375,
      "z": 51.0011177,
      "tags": [
        "CWArm12",
        "CCWArm12"
      ]
    },
    {
      "id": 2,
      "x": 59.71822,
      "z": -127.61451,
      "tags": [
        "CWArm34",
        "CCWArm34"
      ]
    },
    {
      "id": 3,
      "x": 44.22615,
      "z": 140.9998,
      "tags": [
        "CWArm20",
        "CCWArm20"
      ]
    },
    {
      "id": 4,
      "x": -133.540314,
      "z": -77.3889847,
      "tags": [
        "CWArm6",
        "CCWArm6"
      ]
    },
    {
      "id": 5,
      "x": 156.8994,
      "z": -34.493885,
      "tags": [
        "CWArm29",
        "CCWArm29"
      ]
    },
    {
      "id": 6,
      "x": -95.88045,
      "z": 136.379471,
      "tags": [
        "CWArm15",
        "CCWArm15"
      ]
    },
    {
      "id": 7,
      "x": -22.1763115,
      "z": -171.130951,
      "tags": [
        "CWArm1",
        "CCWArm1"
      ]
    },
    {
      "id": 8,
      "x": 136.276764,
      "z": 114.853851,
      "tags": [
        "CWArm23",
        "CCWArm23"
      ]
    },
    {
      "id": 9,
      "x": -183.54921,
      "z": 7.590571,
      "tags": [
        "CWArm10",
        "CCWArm10"
      ]
    },
    {
      "id": 10,
      "x": 133.9913,
      "z": -133.339554,
      "tags": [
        "CWArm32",
        "CCWArm32"
      ]
    },
    {
      "id": 11,
      "x": -8.970741,
      "z": 194.004669,
      "tags": [
        "CWArm18",
        "CCWArm18"
      ]
    },
    {
      "id": 12,
      "x": -127.666069,
      "z": -152.986374,
      "tags": [
        "CWArm4",
        "CCWArm4"
      ]
    },
    {
      "id": 13,
      "x": 202.3545,
      "z": 27.2263756,
      "tags": [
        "CWArm27",
        "CCWArm27"
      ]
    },
    {
      "id": 14,
      "x": -171.5452,
      "z": 119.356812,
      "tags": [
        "CWArm13",
        "CCWArm13"
      ]
    },
    {
      "id": 15,
      "x": 46.8978157,
      "z": -208.469589,
      "tags": [
        "CWArm35",
        "CCWArm35"
      ]
    },
    {
      "id": 16,
      "x": 108.523125,
      "z": 189.385544,
      "tags": [
        "CWArm21",
        "CCWArm21"
      ]
    },
    {
      "id": 17,
      "x": -212.237473,
      "z": -67.70952,
      "tags": [
        "CWArm8",
        "CCWArm8"
      ]
    },
    {
      "id": 18,
      "x": 206.239456,
      "z": -95.28785,
      "tags": [
        "CWArm30",
        "CCWArm30"
      ]
    },
    {
      "id": 19,
      "x": -89.37854,
      "z": 213.567627,
      "tags": [
        "CWArm16",
        "CCWArm16"
      ]
    },
    {
      "id": 20,
      "x": -79.79405,
      "z": -221.850723,
      "tags": [
        "CWArm2",
        "CCWArm2"
      ]
    },
    {
      "id": 21,
      "x": 212.3905,
      "z": 111.6256,
      "tags": [
        "CWArm25",
        "CCWArm25"
      ]
    },
    {
      "id": 22,
      "x": -235.978516,
      "z": 62.20397,
      "tags": [
        "CWArm11",
        "CCWArm11"
      ]
    },
    {
      "id": 23,
      "x": 134.166748,
      "z": -208.661514,
      "tags": [
        "CWArm33",
        "CCWArm33"
      ]
    },
    {
      "id": 24,
      "x": 42.6907349,
      "z": 248.400925,
      "tags": [
        "CWArm19",
        "CCWArm19"
      ]
    },
    {
      "id": 25,
      "x": -202.360886,
      "z": -156.718765,
      "tags": [
        "CWArm6",
        "CCWArm6"
      ]
    },
    {
      "id": 26,
      "x": 258.9126,
      "z": -21.4510441,
      "tags": [
        "CWArm28",
        "CCWArm28"
      ]
    },
    {
      "id": 27,
      "x": -178.9998,
      "z": 193.494492,
      "tags": [
        "CWArm14",
        "CCWArm14"
      ]
    },
    {
      "id": 28,
      "x": 1.30351388,
      "z": -267.328461,
      "tags": [
        "CWArm36",
        "CCWArm36"
      ]
    },
    {
      "id": 29,
      "x": 182.0942,
      "z": 200.731415,
      "tags": [
        "CWArm23",
        "CCWArm23"
      ]
    },
    {
      "id": 30,
      "x": -273.4852,
      "z": -25.3460026,
      "tags": [
        "CWArm9",
        "CCWArm9"
      ]
    },
    {
      "id": 31,
      "x": 221.640472,
      "z": -168.21785,
      "tags": [
        "CWArm31",
        "CCWArm31"
      ]
    },
    {
      "id": 32,
      "x": -50.4357338,
      "z": 277.242035,
      "tags": [
        "CWArm17",
        "CCWArm17"
      ]
    },
    {
      "id": 33,
      "x": -151.950836,
      "z": -241.4602,
      "tags": [
        "CWArm4",
        "CCWArm4"
      ]
    },
    {
      "id": 34,
      "x": 278.482483,
      "z": 76.32009,
      "tags": [
        "CWArm26",
        "CCWArm26"
      ]
    },
    {
      "id": 35,
      "x": -259.9381,
      "z": 133.396347,
      "tags": [
        "CWArm12",
        "CCWArm12"
      ]
    },
    {
      "id": 36,
      "x": 102.736557,
      "z": -277.1151,
      "tags": [
        "CWArm34",
        "CCWArm34"
      ]
    },
    {
      "id": 37,
      "x": 112.692978,
      "z": 276.826752,
      "tags": [
        "CWArm21",
        "CCWArm21"
      ]
    },
    {
      "id": 38,
      "x": -273.075562,
      "z": -129.4128,
      "tags": [
        "CWArm7",
        "CCWArm7"
      ]
    },
    {
      "id": 39,
      "x": 291.897217,
      "z": -89.99522,
      "tags": [
        "CWArm29",
        "CCWArm29"
      ]
    },
    {
      "id": 40,
      "x": -156.0774,
      "z": 266.323364,
      "tags": [
        "CWArm15",
        "CCWArm15"
      ]
    },
    {
      "id": 41,
      "x": -65.48151,
      "z": -304.935455,
      "tags": [
        "CWArm2",
        "CCWArm2"
      ]
    },
    {
      "id": 42,
      "x": 256.846375,
      "z": 182.451553,
      "tags": [
        "CWArm24",
        "CCWArm24"
      ]
    },
    {
      "id": 43,
      "x": -315.7457,
      "z": 39.35078,
      "tags": [
        "CWArm10",
        "CCWArm10"
      ]
    },
    {
      "id": 44,
      "x": 208.252136,
      "z": -244.663086,
      "tags": [
        "CWArm32",
        "CCWArm32"
      ]
    },
    {
      "id": 45,
      "x": 11.8233747,
      "z": 324.151764,
      "tags": [
        "CWArm19",
        "CCWArm19"
      ]
    },
    {
      "id": 46,
      "x": -229.8174,
      "z": -233.202225,
      "tags": [
        "CWArm5",
        "CCWArm5"
      ]
    },
    {
      "id": 47,
      "x": 329.9998,
      "z": 16.8707771,
      "tags": [
        "CWArm27",
        "CCWArm27"
      ]
    },
    {
      "id": 48,
      "x": -257.0362,
      "z": 212.372482,
      "tags": [
        "CWArm13",
        "CCWArm13"
      ]
    },
    {
      "id": 49,
      "x": 46.4794579,
      "z": -333.158356,
      "tags": [
        "CWArm36",
        "CCWArm36"
      ]
    },
    {
      "id": 50,
      "x": 192.438858,
      "z": 279.476837,
      "tags": [
        "CWArm22",
        "CCWArm22"
      ]
    },
    {
      "id": 51,
      "x": -333.520844,
      "z": -76.7401,
      "tags": [
        "CWArm8",
        "CCWArm8"
      ]
    },
    {
      "id": 52,
      "x": 300.277954,
      "z": -170.127975,
      "tags": [
        "CWArm30",
        "CCWArm30"
      ]
    },
    {
      "id": 53,
      "x": -107.379662,
      "z": 331.006256,
      "tags": [
        "CWArm17",
        "CCWArm17"
      ]
    },
    {
      "id": 54,
      "x": -145.591949,
      "z": -319.1922,
      "tags": [
        "CWArm3",
        "CCWArm3"
      ]
    },
    {
      "id": 55,
      "x": 325.560364,
      "z": 138.117081,
      "tags": [
        "CWArm25",
        "CCWArm25"
      ]
    },
    {
      "id": 56,
      "x": -335.9901,
      "z": 119.00296,
      "tags": [
        "CWArm11",
        "CCWArm11"
      ]
    },
    {
      "id": 57,
      "x": 168.6658,
      "z": -317.156219,
      "tags": [
        "CWArm34",
        "CCWArm34"
      ]
    },
    {
      "id": 58,
      "x": 90.5556259,
      "z": 350.4584,
      "tags": [
        "CWArm20",
        "CCWArm20"
      ]
    },
    {
      "id": 59,
      "x": -305.7947,
      "z": -198.736359,
      "tags": [
        "CWArm6",
        "CCWArm6"
      ]
    },
    {
      "id": 60,
      "x": 362.402618,
      "z": -60.4655457,
      "tags": [
        "CWArm28",
        "CCWArm28"
      ]
    },
    {
      "id": 61,
      "x": -228.039047,
      "z": 291.504883,
      "tags": [
        "CWArm15",
        "CCWArm15"
      ]
    },
    {
      "id": 62,
      "x": -28.9674263,
      "z": -371.649,
      "tags": [
        "CWArm1",
        "CCWArm1"
      ]
    },
    {
      "id": 63,
      "x": 274.34375,
      "z": 256.286438,
      "tags": [
        "CWArm23",
        "CCWArm23"
      ]
    },
    {
      "id": 64,
      "x": -378.046082,
      "z": -3.68685055,
      "tags": [
        "CWArm9",
        "CCWArm9"
      ]
    },
    {
      "id": 65,
      "x": 283.196259,
      "z": -254.3963,
      "tags": [
        "CWArm32",
        "CCWArm32"
      ]
    },
    {
      "id": 66,
      "x": -37.23036,
      "z": 381.4665,
      "tags": [
        "CWArm18",
        "CCWArm18"
      ]
    },
    {
      "id": 67,
      "x": -231.774719,
      "z": -308.493835,
      "tags": [
        "CWArm4",
        "CCWArm4"
      ]
    },
    {
      "id": 68,
      "x": 381.808258,
      "z": 71.38343,
      "tags": [
        "CWArm26",
        "CCWArm26"
      ]
    },
    {
      "id": 69,
      "x": -331.914673,
      "z": 206.617859,
      "tags": [
        "CWArm13",
        "CCWArm13"
      ]
    },
    {
      "id": 70,
      "x": 105.856,
      "z": -378.996,
      "tags": [
        "CWArm35",
        "CCWArm35"
      ]
    },
    {
      "id": 71,
      "x": 179.090225,
      "z": 353.207184,
      "tags": [
        "CWArm21",
        "CCWArm21"
      ]
    },
    {
      "id": 72,
      "x": -372.982056,
      "z": -140.350266,
      "tags": [
        "CWArm7",
        "CCWArm7"
      ]
    },
    {
      "id": 73,
      "x": 372.134857,
      "z": -149.380722,
      "tags": [
        "CWArm30",
        "CCWArm30"
      ]
    },
    {
      "id": 74,
      "x": -174.557648,
      "z": 363.749664,
      "tags": [
        "CWArm16",
        "CCWArm16"
      ]
    },
    {
      "id": 75,
      "x": -117.701218,
      "z": -388.4788,
      "tags": [
        "CWArm2",
        "CCWArm2"
      ]
    },
    {
      "id": 76,
      "x": 351.3001,
      "z": 208.1891,
      "tags": [
        "CWArm24",
        "CCWArm24"
      ]
    },
    {
      "id": 77,
      "x": -402.0382,
      "z": 84.2910156,
      "tags": [
        "CWArm11",
        "CCWArm11"
      ]
    },
    {
      "id": 78,
      "x": 240.922653,
      "z": -335.680084,
      "tags": [
        "CWArm33",
        "CCWArm33"
      ]
    },
    {
      "id": 79,
      "x": 49.3843842,
      "z": 412.6393,
      "tags": [
        "CWArm19",
        "CCWArm19"
      ]
    },
    {
      "id": 80,
      "x": -316.954346,
      "z": -272.461273,
      "tags": [
        "CWArm5",
        "CCWArm5"
      ]
    },
    {
      "id": 81,
      "x": 420.1239,
      "z": -13.2762318,
      "tags": [
        "CWArm28",
        "CCWArm28"
      ]
    },
    {
      "id": 82,
      "x": -302.508118,
      "z": 295.219147,
      "tags": [
        "CWArm14",
        "CCWArm14"
      ]
    },
    {
      "id": 83,
      "x": 23.77347,
      "z": -424.364868,
      "tags": [
        "CWArm36",
        "CCWArm36"
      ]
    },
    {
      "id": 84,
      "x": 270.604218,
      "z": 330.770721,
      "tags": [
        "CWArm22",
        "CCWArm22"
      ]
    },
    {
      "id": 85,
      "x": -425.259125,
      "z": -61.44729,
      "tags": [
        "CWArm9",
        "CCWArm9"
      ]
    },
    {
      "id": 86,
      "x": 356.983826,
      "z": -243.246353,
      "tags": [
        "CWArm31",
        "CCWArm31"
      ]
    },
    {
      "id": 87,
      "x": -99.44306,
      "z": 422.7322,
      "tags": [
        "CWArm17",
        "CCWArm17"
      ]
    },
    {
      "id": 88,
      "x": -213.345078,
      "z": -380.868042,
      "tags": [
        "CWArm3",
        "CCWArm3"
      ]
    },
    {
      "id": 89,
      "x": 416.73822,
      "z": 137.444412,
      "tags": [
        "CWArm26",
        "CCWArm26"
      ]
    },
    {
      "id": 90,
      "x": -402.189484,
      "z": 181.0816,
      "tags": [
        "CWArm12",
        "CCWArm12"
      ]
    },
    {
      "id": 91,
      "x": 175.123688,
      "z": -407.263733,
      "tags": [
        "CWArm34",
        "CCWArm34"
      ]
    },
    {
      "id": 92,
      "x": 146.700851,
      "z": 420.709076,
      "tags": [
        "CWArm20",
        "CCWArm20"
      ]
    },
    {
      "id": 93,
      "x": -394.314362,
      "z": -212.175812,
      "tags": [
        "CWArm7",
        "CCWArm7"
      ]
    },
    {
      "id": 94,
      "x": 436.221466,
      "z": -110.446381,
      "tags": [
        "CWArm29",
        "CCWArm29"
      ]
    },
    {
      "id": 95,
      "x": -248.253067,
      "z": 377.946,
      "tags": [
        "CWArm15",
        "CCWArm15"
      ]
    },
    {
      "id": 96,
      "x": -72.5877151,
      "z": -448.540924,
      "tags": [
        "CWArm1",
        "CCWArm1"
      ]
    },
    {
      "id": 97,
      "x": 358.218842,
      "z": 283.059,
      "tags": [
        "CWArm24",
        "CCWArm24"
      ]
    },
    {
      "id": 98,
      "x": -457.5057,
      "z": 33.419323,
      "tags": [
        "CWArm10",
        "CCWArm10"
      ]
    },
    {
      "id": 99,
      "x": 316.257355,
      "z": -335.253235,
      "tags": [
        "CWArm32",
        "CCWArm32"
      ]
    },
    {
      "id": 100,
      "x": -6.76951,
      "z": 462.982483,
      "tags": [
        "CWArm18",
        "CCWArm18"
      ]
    },
    {
      "id": 101,
      "x": -309.17,
      "z": -347.5597,
      "tags": [
        "CWArm5",
        "CCWArm5"
      ]
    },
    {
      "id": 102,
      "x": 464.863373,
      "z": 47.6555328,
      "tags": [
        "CWArm27",
        "CCWArm27"
      ]
    },
    {
      "id": 103,
      "x": -376.667236,
      "z": 280.135651,
      "tags": [
        "CWArm13",
        "CCWArm13"
      ]
    },
    {
      "id": 104,
      "x": 88.92577,
      "z": -463.067566,
      "tags": [
        "CWArm35",
        "CCWArm35"
      ]
    },
    {
      "id": 105,
      "x": 248.340012,
      "z": 403.301025,
      "tags": [
        "CWArm22",
        "CCWArm22"
      ]
    },
    {
      "id": 106,
      "x": -457.5554,
      "z": -130.202774,
      "tags": [
        "CWArm8",
        "CCWArm8"
      ]
    },
    {
      "id": 107,
      "x": 427.1993,
      "z": -213.999146,
      "tags": [
        "CWArm30",
        "CCWArm30"
      ]
    },
    {
      "id": 108,
      "x": -171.188644,
      "z": 448.3018,
      "tags": [
        "CWArm16",
        "CCWArm16"
      ]
    },
    {
      "id": 109,
      "x": -177.353775,
      "z": -448.119232,
      "tags": [
        "CWArm3",
        "CCWArm3"
      ]
    },
    {
      "id": 110,
      "x": 435.323853,
      "z": 211.526688,
      "tags": [
        "CWArm25",
        "CCWArm25"
      ]
    },
    {
      "id": 111,
      "x": -465.839935,
      "z": 138.667633,
      "tags": [
        "CWArm11",
        "CCWArm11"
      ]
    },
    {
      "id": 112,
      "x": 250.8748,
      "z": -418.667633,
      "tags": [
        "CWArm33",
        "CCWArm33"
      ]
    },
    {
      "id": 113,
      "x": 98.225296,
      "z": 480.1642,
      "tags": [
        "CWArm20",
        "CCWArm20"
      ]
    },
    {
      "id": 114,
      "x": -398.4107,
      "z": -288.8944,
      "tags": [
        "CWArm6",
        "CCWArm6"
      ]
    },
    {
      "id": 115,
      "x": 490.9207,
      "z": -56.3302,
      "tags": [
        "CWArm28",
        "CCWArm28"
      ]
    },
    {
      "id": 116,
      "x": -325.2534,
      "z": 374.662079,
      "tags": [
        "CWArm14",
        "CCWArm14"
      ]
    },
    {
      "id": 117,
      "x": -13.3021135,
      "z": -497.965454,
      "tags": [
        "CWArm1",
        "CCWArm1"
      ]
    },
    {
      "id": 118,
      "x": 347.56134,
      "z": 359.6288,
      "tags": [
        "CWArm23",
        "CCWArm23"
      ]
    },
    {
      "id": 119,
      "x": -501.183746,
      "z": -30.52527,
      "tags": [
        "CWArm9",
        "CCWArm9"
      ]
    },
    {
      "id": 120,
      "x": 391.70993,
      "z": -317.2781,
      "tags": [
        "CWArm31",
        "CCWArm31"
      ]
    },
    {
      "id": 121,
      "x": -74.80706,
      "z": 500.490936,
      "tags": [
        "CWArm18",
        "CCWArm18"
      ]
    },
    {
      "id": 122,
      "x": -284.010773,
      "z": -421.201019,
      "tags": [
        "CWArm4",
        "CCWArm4"
      ]
    },
    {
      "id": 123,
      "x": 495.834045,
      "z": 119.189896,
      "tags": [
        "CWArm26",
        "CCWArm26"
      ]
    },
    {
      "id": 124,
      "x": -447.8238,
      "z": 247.985214,
      "tags": [
        "CWArm12",
        "CCWArm12"
      ]
    },
    {
      "id": 125,
      "x": 163.314911,
      "z": -487.1921,
      "tags": [
        "CWArm35",
        "CCWArm35"
      ]
    },
    {
      "id": 126,
      "x": 209.453186,
      "z": 471.319946,
      "tags": [
        "CWArm21",
        "CCWArm21"
      ]
    },
    {
      "id": 127,
      "x": -474.5772,
      "z": -206.820541,
      "tags": [
        "CWArm7",
        "CCWArm7"
      ]
    },
    {
      "id": 128,
      "x": 491.453949,
      "z": -168.690536,
      "tags": [
        "CWArm29",
        "CCWArm29"
      ]
    },
    {
      "id": 129,
      "x": -249.345779,
      "z": 458.034149,
      "tags": [
        "CWArm16",
        "CCWArm16"
      ]
    },
    {
      "id": 130,
      "x": -125.9951,
      "z": -508.014862,
      "tags": [
        "CWArm2",
        "CCWArm2"
      ]
    },
    {
      "id": 131,
      "x": 437.641,
      "z": 290.5329,
      "tags": [
        "CWArm24",
        "CCWArm24"
      ]
    },
    {
      "id": 132,
      "x": -520.8185,
      "z": 81.68452,
      "tags": [
        "CWArm10",
        "CCWArm10"
      ]
    },
    {
      "id": 133,
      "x": 330.03064,
      "z": -413.50827,
      "tags": [
        "CWArm33",
        "CCWArm33"
      ]
    },
    {
      "id": 134,
      "x": 36.0937347,
      "z": 529.7091,
      "tags": [
        "CWArm19",
        "CCWArm19"
      ]
    },
    {
      "id": 135,
      "x": -385.7789,
      "z": -367.4973,
      "tags": [
        "CWArm5",
        "CCWArm5"
      ]
    },
    {
      "id": 136,
      "x": 534.561646,
      "z": 10.4274912,
      "tags": [
        "CWArm27",
        "CCWArm27"
      ]
    },
    {
      "id": 137,
      "x": -402.6035,
      "z": 354.627167,
      "tags": [
        "CWArm14",
        "CCWArm14"
      ]
    },
    {
      "id": 138,
      "x": 57.5174751,
      "z": -535.2821,
      "tags": [
        "CWArm36",
        "CCWArm36"
      ]
    },
    {
      "id": 139,
      "x": 320.2574,
      "z": 435.035156,
      "tags": [
        "CWArm22",
        "CCWArm22"
      ]
    },
    {
      "id": 140,
      "x": -531.8095,
      "z": -104.805374,
      "tags": [
        "CWArm8",
        "CCWArm8"
      ]
    },
    {
      "id": 141,
      "x": 464.496216,
      "z": -282.9028,
      "tags": [
        "CWArm31",
        "CCWArm31"
      ]
    },
    {
      "id": 142,
      "x": -151.914246,
      "z": 524.1164,
      "tags": [
        "CWArm17",
        "CCWArm17"
      ]
    },
    {
      "id": 143,
      "x": -242.82402,
      "z": -490.711334,
      "tags": [
        "CWArm3",
        "CCWArm3"
      ]
    },
    {
      "id": 144,
      "x": 512.2092,
      "z": 198.463959,
      "tags": [
        "CWArm25",
        "CCWArm25"
      ]
    },
    {
      "id": 145,
      "x": -513.428345,
      "z": 200.3068,
      "tags": [
        "CWArm12",
        "CCWArm12"
      ]
    },
    {
      "id": 146,
      "x": 244.074539,
      "z": -496.1292,
      "tags": [
        "CWArm34",
        "CCWArm34"
      ]
    },
    {
      "id": 147,
      "x": 155.660355,
      "z": 532.4206,
      "tags": [
        "CWArm20",
        "CCWArm20"
      ]
    },
    {
      "id": 148,
      "x": -475.9519,
      "z": -288.3691,
      "tags": [
        "CWArm6",
        "CCWArm6"
      ]
    },
    {
      "id": 149,
      "x": 547.4891,
      "z": -109.21479,
      "tags": [
        "CWArm29",
        "CCWArm29"
      ]
    },
    {
      "id": 150,
      "x": -330.976959,
      "z": 451.787048,
      "tags": [
        "CWArm15",
        "CCWArm15"
      ]
    }
  ],
  "outputs": [],
  "wirePaths": [
    {
      "pathId": "0",
      "artnetHost": "192.168.0.220",
      "universe": 1,
      "channelStart": 0,
      "generator": 0,
      "items": [
        {
          "FixtureType": "PlantFixture",
          "FixtureId": 0,
          "PathId": 0,
          "ChannelStartOverride": -1
        },
        {
          "FixtureType": "PlantFixture",
          "FixtureId": 8,
          "PathId": 1,
          "ChannelStartOverride": -1
        },
        {
          "FixtureType": "PlantFixture",
          "FixtureId": 16,
          "PathId": 2,
          "ChannelStartOverride": -1
        },
        {
          "FixtureType": "PlantFixture",
          "FixtureId": 37,
          "PathId": 3,
          "ChannelStartOverride": -1
        },
        {
          "FixtureType": "PlantFixture",
          "FixtureId": 58,
          "PathId": 4,
          "ChannelStartOverride": -1
        },
        {
          "FixtureType": "PlantFixture",
          "FixtureId": 79,
          "PathId": 5,
          "ChannelStartOverride": -1
        },
        {
          "FixtureType": "PlantFixture",
          "FixtureId": 100,
          "PathId": 6,
          "ChannelStartOverride": -1
        },
        {
          "FixtureType": "PlantFixture",
          "FixtureId": 121,
          "PathId": 7,
          "ChannelStartOverride": -1
        },
        {
          "FixtureType": "PlantFixture",
          "FixtureId": 142,
          "PathId": 8,
          "ChannelStartOverride": -1
        }
      ]
    },
    {
      "pathId": "1",
      "artnetHost": "192.168.0.220",
      "universe": 2,
      "channelStart": 0,
      "generator": 0,
      "items": [
        {
          "FixtureType": "PlantFixture",
          "FixtureId": 29,
          "PathId": 0,
          "ChannelStartOverride": -1
        },
        {
          "FixtureType": "PlantFixture",
          "FixtureId": 50,
          "PathId": 1,
          "ChannelStartOverride": -1
        },
        {
          "FixtureType": "PlantFixture",
          "FixtureId": 71,
          "PathId": 2,
          "ChannelStartOverride": -1
        },
        {
          "FixtureType": "PlantFixture",
          "FixtureId": 92,
          "PathId": 3,
          "ChannelStartOverride": -1
        },
        {
          "FixtureType": "PlantFixture",
          "FixtureId": 113,
          "PathId": 4,
          "ChannelStartOverride": -1
        },
        {
          "FixtureType": "PlantFixture",
          "FixtureId": 134,
          "PathId": 5,
          "ChannelStartOverride": -1
        }
      ]
    },
    {
      "pathId": "2",
      "artnetHost": "192.168.0.220",
      "universe": 3,
      "channelStart": 0,
      "generator": 0,
      "items": [
        {
          "FixtureType": "PlantFixture",
          "FixtureId": 5,
          "PathId": 0,
          "ChannelStartOverride": -1
        },
        {
          "FixtureType": "PlantFixture",
          "FixtureId": 13,
          "PathId": 1,
          "ChannelStartOverride": -1
        },
        {
          "FixtureType": "PlantFixture",
          "FixtureId": 21,
          "PathId": 2,
          "ChannelStartOverride": -1
        },
        {
          "FixtureType": "PlantFixture",
          "FixtureId": 42,
          "PathId": 3,
          "ChannelStartOverride": -1
        },
        {
          "FixtureType": "PlantFixture",
          "FixtureId": 63,
          "PathId": 4,
          "ChannelStartOverride": -1
        },
        {
          "FixtureType": "PlantFixture",
          "FixtureId": 84,
          "PathId": 5,
          "ChannelStartOverride": -1
        },
        {
          "FixtureType": "PlantFixture",
          "FixtureId": 105,
          "PathId": 6,
          "ChannelStartOverride": -1
        },
        {
          "FixtureType": "PlantFixture",
          "FixtureId": 126,
          "PathId": 7,
          "ChannelStartOverride": -1
        },
        {
          "FixtureType": "PlantFixture",
          "FixtureId": 147,
          "PathId": 8,
          "ChannelStartOverride": -1
        }
      ]
    },
    {
      "pathId": "3",
      "artnetHost": "192.168.0.220",
      "universe": 4,
      "channelStart": 0,
      "generator": 0,
      "items": [
        {
          "FixtureType": "PlantFixture",
          "FixtureId": 34,
          "PathId": 0,
          "ChannelStartOverride": -1
        },
        {
          "FixtureType": "PlantFixture",
          "FixtureId": 55,
          "PathId": 1,
          "ChannelStartOverride": -1
        },
        {
          "FixtureType": "PlantFixture",
          "FixtureId": 76,
          "PathId": 2,
          "ChannelStartOverride": -1
        },
        {
          "FixtureType": "PlantFixture",
          "FixtureId": 97,
          "PathId": 3,
          "ChannelStartOverride": -1
        },
        {
          "FixtureType": "PlantFixture",
          "FixtureId": 118,
          "PathId": 4,
          "ChannelStartOverride": -1
        },
        {
          "FixtureType": "PlantFixture",
          "FixtureId": 139,
          "PathId": 5,
          "ChannelStartOverride": -1
        }
      ]
    },
    {
      "pathId": "4",
      "artnetHost": "192.168.0.221",
      "universe": 1,
      "channelStart": 0,
      "generator": 0,
      "items": [
        {
          "FixtureType": "PlantFixture",
          "FixtureId": 26,
          "PathId": 0,
          "ChannelStartOverride": -1
        },
        {
          "FixtureType": "PlantFixture",
          "FixtureId": 47,
          "PathId": 1,
          "ChannelStartOverride": -1
        },
        {
          "FixtureType": "PlantFixture",
          "FixtureId": 68,
          "PathId": 2,
          "ChannelStartOverride": -1
        },
        {
          "FixtureType": "PlantFixture",
          "FixtureId": 89,
          "PathId": 3,
          "ChannelStartOverride": -1
        },
        {
          "FixtureType": "PlantFixture",
          "FixtureId": 110,
          "PathId": 4,
          "ChannelStartOverride": -1
        },
        {
          "FixtureType": "PlantFixture",
          "FixtureId": 131,
          "PathId": 5,
          "ChannelStartOverride": -1
        }
      ]
    },
    {
      "pathId": "5",
      "artnetHost": "192.168.0.221",
      "universe": 2,
      "channelStart": 0,
      "generator": 0,
      "items": [
        {
          "FixtureType": "PlantFixture",
          "FixtureId": 18,
          "PathId": 0,
          "ChannelStartOverride": -1
        },
        {
          "FixtureType": "PlantFixture",
          "FixtureId": 39,
          "PathId": 1,
          "ChannelStartOverride": -1
        },
        {
          "FixtureType": "PlantFixture",
          "FixtureId": 60,
          "PathId": 2,
          "ChannelStartOverride": -1
        },
        {
          "FixtureType": "PlantFixture",
          "FixtureId": 81,
          "PathId": 3,
          "ChannelStartOverride": -1
        },
        {
          "FixtureType": "PlantFixture",
          "FixtureId": 102,
          "PathId": 4,
          "ChannelStartOverride": -1
        },
        {
          "FixtureType": "PlantFixture",
          "FixtureId": 123,
          "PathId": 5,
          "ChannelStartOverride": -1
        },
        {
          "FixtureType": "PlantFixture",
          "FixtureId": 144,
          "PathId": 6,
          "ChannelStartOverride": -1
        }
      ]
    },
    {
      "pathId": "6",
      "artnetHost": "192.168.0.221",
      "universe": 3,
      "channelStart": 0,
      "generator": 0,
      "items": [
        {
          "FixtureType": "PlantFixture",
          "FixtureId": 2,
          "PathId": 0,
          "ChannelStartOverride": -1
        },
        {
          "FixtureType": "PlantFixture",
          "FixtureId": 10,
          "PathId": 1,
          "ChannelStartOverride": -1
        },
        {
          "FixtureType": "PlantFixture",
          "FixtureId": 31,
          "PathId": 2,
          "ChannelStartOverride": -1
        },
        {
          "FixtureType": "PlantFixture",
          "FixtureId": 52,
          "PathId": 3,
          "ChannelStartOverride": -1
        },
        {
          "FixtureType": "PlantFixture",
          "FixtureId": 73,
          "PathId": 4,
          "ChannelStartOverride": -1
        },
        {
          "FixtureType": "PlantFixture",
          "FixtureId": 94,
          "PathId": 5,
          "ChannelStartOverride": -1
        },
        {
          "FixtureType": "PlantFixture",
          "FixtureId": 115,
          "PathId": 6,
          "ChannelStartOverride": -1
        },
        {
          "FixtureType": "PlantFixture",
          "FixtureId": 136,
          "PathId": 7,
          "ChannelStartOverride": -1
        }
      ]
    },
    {
      "pathId": "7",
      "artnetHost": "192.168.0.221",
      "universe": 4,
      "channelStart": 0,
      "generator": 0,
      "items": [
        {
          "FixtureType": "PlantFixture",
          "FixtureId": 23,
          "PathId": 0,
          "ChannelStartOverride": -1
        },
        {
          "FixtureType": "PlantFixture",
          "FixtureId": 44,
          "PathId": 1,
          "ChannelStartOverride": -1
        },
        {
          "FixtureType": "PlantFixture",
          "FixtureId": 65,
          "PathId": 2,
          "ChannelStartOverride": -1
        },
        {
          "FixtureType": "PlantFixture",
          "FixtureId": 86,
          "PathId": 3,
          "ChannelStartOverride": -1
        },
        {
          "FixtureType": "PlantFixture",
          "FixtureId": 107,
          "PathId": 4,
          "ChannelStartOverride": -1
        },
        {
          "FixtureType": "PlantFixture",
          "FixtureId": 128,
          "PathId": 5,
          "ChannelStartOverride": -1
        },
        {
          "FixtureType": "PlantFixture",
          "FixtureId": 149,
          "PathId": 6,
          "ChannelStartOverride": -1
        }
      ]
    },
    {
      "pathId": "8",
      "artnetHost": "192.168.0.222",
      "universe": 1,
      "channelStart": 0,
      "generator": 0,
      "items": [
        {
          "FixtureType": "PlantFixture",
          "FixtureId": 7,
          "PathId": 0,
          "ChannelStartOverride": -1
        },
        {
          "FixtureType": "PlantFixture",
          "FixtureId": 15,
          "PathId": 1,
          "ChannelStartOverride": -1
        },
        {
          "FixtureType": "PlantFixture",
          "FixtureId": 36,
          "PathId": 2,
          "ChannelStartOverride": -1
        },
        {
          "FixtureType": "PlantFixture",
          "FixtureId": 57,
          "PathId": 3,
          "ChannelStartOverride": -1
        },
        {
          "FixtureType": "PlantFixture",
          "FixtureId": 78,
          "PathId": 4,
          "ChannelStartOverride": -1
        },
        {
          "FixtureType": "PlantFixture",
          "FixtureId": 99,
          "PathId": 5,
          "ChannelStartOverride": -1
        },
        {
          "FixtureType": "PlantFixture",
          "FixtureId": 120,
          "PathId": 6,
          "ChannelStartOverride": -1
        },
        {
          "FixtureType": "PlantFixture",
          "FixtureId": 141,
          "PathId": 7,
          "ChannelStartOverride": -1
        }
      ]
    },
    {
      "pathId": "9",
      "artnetHost": "192.168.0.222",
      "universe": 2,
      "channelStart": 0,
      "generator": 0,
      "items": [
        {
          "FixtureType": "PlantFixture",
          "FixtureId": 28,
          "PathId": 0,
          "ChannelStartOverride": -1
        },
        {
          "FixtureType": "PlantFixture",
          "FixtureId": 49,
          "PathId": 1,
          "ChannelStartOverride": -1
        },
        {
          "FixtureType": "PlantFixture",
          "FixtureId": 70,
          "PathId": 2,
          "ChannelStartOverride": -1
        },
        {
          "FixtureType": "PlantFixture",
          "FixtureId": 91,
          "PathId": 3,
          "ChannelStartOverride": -1
        },
        {
          "FixtureType": "PlantFixture",
          "FixtureId": 112,
          "PathId": 4,
          "ChannelStartOverride": -1
        },
        {
          "FixtureType": "PlantFixture",
          "FixtureId": 133,
          "PathId": 5,
          "ChannelStartOverride": -1
        }
      ]
    },
    {
      "pathId": "10",
      "artnetHost": "192.168.0.222",
      "universe": 3,
      "channelStart": 0,
      "generator": 0,
      "items": [
        {
          "FixtureType": "PlantFixture",
          "FixtureId": 20,
          "PathId": 0,
          "ChannelStartOverride": -1
        },
        {
          "FixtureType": "PlantFixture",
          "FixtureId": 41,
          "PathId": 1,
          "ChannelStartOverride": -1
        },
        {
          "FixtureType": "PlantFixture",
          "FixtureId": 62,
          "PathId": 2,
          "ChannelStartOverride": -1
        },
        {
          "FixtureType": "PlantFixture",
          "FixtureId": 83,
          "PathId": 3,
          "ChannelStartOverride": -1
        },
        {
          "FixtureType": "PlantFixture",
          "FixtureId": 104,
          "PathId": 4,
          "ChannelStartOverride": -1
        },
        {
          "FixtureType": "PlantFixture",
          "FixtureId": 125,
          "PathId": 5,
          "ChannelStartOverride": -1
        },
        {
          "FixtureType": "PlantFixture",
          "FixtureId": 146,
          "PathId": 6,
          "ChannelStartOverride": -1
        }
      ]
    },
    {
      "pathId": "11",
      "artnetHost": "192.168.0.222",
      "universe": 4,
      "channelStart": 0,
      "generator": 0,
      "items": [
        {
          "FixtureType": "PlantFixture",
          "FixtureId": 12,
          "PathId": 0,
          "ChannelStartOverride": -1
        },
        {
          "FixtureType": "PlantFixture",
          "FixtureId": 33,
          "PathId": 1,
          "ChannelStartOverride": -1
        },
        {
          "FixtureType": "PlantFixture",
          "FixtureId": 54,
          "PathId": 2,
          "ChannelStartOverride": -1
        },
        {
          "FixtureType": "PlantFixture",
          "FixtureId": 75,
          "PathId": 3,
          "ChannelStartOverride": -1
        },
        {
          "FixtureType": "PlantFixture",
          "FixtureId": 96,
          "PathId": 4,
          "ChannelStartOverride": -1
        },
        {
          "FixtureType": "PlantFixture",
          "FixtureId": 117,
          "PathId": 5,
          "ChannelStartOverride": -1
        },
        {
          "FixtureType": "PlantFixture",
          "FixtureId": 138,
          "PathId": 6,
          "ChannelStartOverride": -1
        }
      ]
    },
    {
      "pathId": "12",
      "artnetHost": "192.168.0.223",
      "universe": 1,
      "channelStart": 0,
      "generator": 0,
      "items": [
        {
          "FixtureType": "PlantFixture",
          "FixtureId": 4,
          "PathId": 0,
          "ChannelStartOverride": -1
        },
        {
          "FixtureType": "PlantFixture",
          "FixtureId": 25,
          "PathId": 1,
          "ChannelStartOverride": -1
        },
        {
          "FixtureType": "PlantFixture",
          "FixtureId": 46,
          "PathId": 2,
          "ChannelStartOverride": -1
        },
        {
          "FixtureType": "PlantFixture",
          "FixtureId": 67,
          "PathId": 3,
          "ChannelStartOverride": -1
        },
        {
          "FixtureType": "PlantFixture",
          "FixtureId": 88,
          "PathId": 4,
          "ChannelStartOverride": -1
        },
        {
          "FixtureType": "PlantFixture",
          "FixtureId": 109,
          "PathId": 5,
          "ChannelStartOverride": -1
        },
        {
          "FixtureType": "PlantFixture",
          "FixtureId": 130,
          "PathId": 6,
          "ChannelStartOverride": -1
        }
      ]
    },
    {
      "pathId": "13",
      "artnetHost": "192.168.0.223",
      "universe": 2,
      "channelStart": 0,
      "generator": 0,
      "items": [
        {
          "FixtureType": "PlantFixture",
          "FixtureId": 17,
          "PathId": 0,
          "ChannelStartOverride": -1
        },
        {
          "FixtureType": "PlantFixture",
          "FixtureId": 38,
          "PathId": 1,
          "ChannelStartOverride": -1
        },
        {
          "FixtureType": "PlantFixture",
          "FixtureId": 59,
          "PathId": 2,
          "ChannelStartOverride": -1
        },
        {
          "FixtureType": "PlantFixture",
          "FixtureId": 80,
          "PathId": 3,
          "ChannelStartOverride": -1
        },
        {
          "FixtureType": "PlantFixture",
          "FixtureId": 101,
          "PathId": 4,
          "ChannelStartOverride": -1
        },
        {
          "FixtureType": "PlantFixture",
          "FixtureId": 122,
          "PathId": 5,
          "ChannelStartOverride": -1
        },
        {
          "FixtureType": "PlantFixture",
          "FixtureId": 143,
          "PathId": 6,
          "ChannelStartOverride": -1
        }
      ]
    },
    {
      "pathId": "14",
      "artnetHost": "192.168.0.223",
      "universe": 3,
      "channelStart": 0,
      "generator": 0,
      "items": [
        {
          "FixtureType": "PlantFixture",
          "FixtureId": 9,
          "PathId": 0,
          "ChannelStartOverride": -1
        },
        {
          "FixtureType": "PlantFixture",
          "FixtureId": 30,
          "PathId": 1,
          "ChannelStartOverride": -1
        },
        {
          "FixtureType": "PlantFixture",
          "FixtureId": 51,
          "PathId": 2,
          "ChannelStartOverride": -1
        },
        {
          "FixtureType": "PlantFixture",
          "FixtureId": 72,
          "PathId": 3,
          "ChannelStartOverride": -1
        },
        {
          "FixtureType": "PlantFixture",
          "FixtureId": 93,
          "PathId": 4,
          "ChannelStartOverride": -1
        },
        {
          "FixtureType": "PlantFixture",
          "FixtureId": 114,
          "PathId": 5,
          "ChannelStartOverride": -1
        },
        {
          "FixtureType": "PlantFixture",
          "FixtureId": 135,
          "PathId": 6,
          "ChannelStartOverride": -1
        }
      ]
    },
    {
      "pathId": "15",
      "artnetHost": "192.168.0.223",
      "universe": 4,
      "channelStart": 0,
      "generator": 0,
      "items": [
        {
          "FixtureType": "PlantFixture",
          "FixtureId": 1,
          "PathId": 0,
          "ChannelStartOverride": -1
        },
        {
          "FixtureType": "PlantFixture",
          "FixtureId": 22,
          "PathId": 1,
          "ChannelStartOverride": -1
        },
        {
          "FixtureType": "PlantFixture",
          "FixtureId": 43,
          "PathId": 2,
          "ChannelStartOverride": -1
        },
        {
          "FixtureType": "PlantFixture",
          "FixtureId": 64,
          "PathId": 3,
          "ChannelStartOverride": -1
        },
        {
          "FixtureType": "PlantFixture",
          "FixtureId": 85,
          "PathId": 4,
          "ChannelStartOverride": -1
        },
        {
          "FixtureType": "PlantFixture",
          "FixtureId": 106,
          "PathId": 5,
          "ChannelStartOverride": -1
        },
        {
          "FixtureType": "PlantFixture",
          "FixtureId": 127,
          "PathId": 6,
          "ChannelStartOverride": -1
        },
        {
          "FixtureType": "PlantFixture",
          "FixtureId": 148,
          "PathId": 7,
          "ChannelStartOverride": -1
        }
      ]
    },
    {
      "pathId": "16",
      "artnetHost": "192.168.0.224",
      "universe": 1,
      "channelStart": 0,
      "generator": 0,
      "items": [
        {
          "FixtureType": "PlantFixture",
          "FixtureId": 14,
          "PathId": 0,
          "ChannelStartOverride": -1
        },
        {
          "FixtureType": "PlantFixture",
          "FixtureId": 35,
          "PathId": 1,
          "ChannelStartOverride": -1
        },
        {
          "FixtureType": "PlantFixture",
          "FixtureId": 56,
          "PathId": 2,
          "ChannelStartOverride": -1
        },
        {
          "FixtureType": "PlantFixture",
          "FixtureId": 77,
          "PathId": 3,
          "ChannelStartOverride": -1
        },
        {
          "FixtureType": "PlantFixture",
          "FixtureId": 98,
          "PathId": 4,
          "ChannelStartOverride": -1
        },
        {
          "FixtureType": "PlantFixture",
          "FixtureId": 119,
          "PathId": 5,
          "ChannelStartOverride": -1
        },
        {
          "FixtureType": "PlantFixture",
          "FixtureId": 140,
          "PathId": 6,
          "ChannelStartOverride": -1
        }
      ]
    },
    {
      "pathId": "17",
      "artnetHost": "192.168.0.224",
      "universe": 2,
      "channelStart": 0,
      "generator": 0,
      "items": [
        {
          "FixtureType": "PlantFixture",
          "FixtureId": 6,
          "PathId": 0,
          "ChannelStartOverride": -1
        },
        {
          "FixtureType": "PlantFixture",
          "FixtureId": 27,
          "PathId": 1,
          "ChannelStartOverride": -1
        },
        {
          "FixtureType": "PlantFixture",
          "FixtureId": 48,
          "PathId": 2,
          "ChannelStartOverride": -1
        },
        {
          "FixtureType": "PlantFixture",
          "FixtureId": 69,
          "PathId": 3,
          "ChannelStartOverride": -1
        },
        {
          "FixtureType": "PlantFixture",
          "FixtureId": 90,
          "PathId": 4,
          "ChannelStartOverride": -1
        },
        {
          "FixtureType": "PlantFixture",
          "FixtureId": 111,
          "PathId": 5,
          "ChannelStartOverride": -1
        },
        {
          "FixtureType": "PlantFixture",
          "FixtureId": 132,
          "PathId": 6,
          "ChannelStartOverride": -1
        }
      ]
    },
    {
      "pathId": "18",
      "artnetHost": "192.168.0.224",
      "universe": 3,
      "channelStart": 0,
      "generator": 0,
      "items": [
        {
          "FixtureType": "PlantFixture",
          "FixtureId": 19,
          "PathId": 0,
          "ChannelStartOverride": -1
        },
        {
          "FixtureType": "PlantFixture",
          "FixtureId": 40,
          "PathId": 1,
          "ChannelStartOverride": -1
        },
        {
          "FixtureType": "PlantFixture",
          "FixtureId": 61,
          "PathId": 2,
          "ChannelStartOverride": -1
        },
        {
          "FixtureType": "PlantFixture",
          "FixtureId": 82,
          "PathId": 3,
          "ChannelStartOverride": -1
        },
        {
          "FixtureType": "PlantFixture",
          "FixtureId": 103,
          "PathId": 4,
          "ChannelStartOverride": -1
        },
        {
          "FixtureType": "PlantFixture",
          "FixtureId": 124,
          "PathId": 5,
          "ChannelStartOverride": -1
        },
        {
          "FixtureType": "PlantFixture",
          "FixtureId": 145,
          "PathId": 6,
          "ChannelStartOverride": -1
        }
      ]
    },
    {
      "pathId": "19",
      "artnetHost": "192.168.0.224",
      "universe": 4,
      "channelStart": 0,
      "generator": 0,
      "items": [
        {
          "FixtureType": "PlantFixture",
          "FixtureId": 3,
          "PathId": 0,
          "ChannelStartOverride": -1
        },
        {
          "FixtureType": "PlantFixture",
          "FixtureId": 11,
          "PathId": 1,
          "ChannelStartOverride": -1
        },
        {
          "FixtureType": "PlantFixture",
          "FixtureId": 32,
          "PathId": 2,
          "ChannelStartOverride": -1
        },
        {
          "FixtureType": "PlantFixture",
          "FixtureId": 53,
          "PathId": 3,
          "ChannelStartOverride": -1
        },
        {
          "FixtureType": "PlantFixture",
          "FixtureId": 74,
          "PathId": 4,
          "ChannelStartOverride": -1
        },
        {
          "FixtureType": "PlantFixture",
          "FixtureId": 95,
          "PathId": 5,
          "ChannelStartOverride": -1
        },
        {
          "FixtureType": "PlantFixture",
          "FixtureId": 116,
          "PathId": 6,
          "ChannelStartOverride": -1
        },
        {
          "FixtureType": "PlantFixture",
          "FixtureId": 137,
          "PathId": 7,
          "ChannelStartOverride": -1
        }
      ]
    },
    {
      "pathId": "20",
      "artnetHost": "192.168.0.225",
      "universe": 1,
      "channelStart": 0,
      "generator": 0,
      "items": [
        {
          "FixtureType": "PlantFixture",
          "FixtureId": 24,
          "PathId": 0,
          "ChannelStartOverride": -1
        },
        {
          "FixtureType": "PlantFixture",
          "FixtureId": 45,
          "PathId": 1,
          "ChannelStartOverride": -1
        },
        {
          "FixtureType": "PlantFixture",
          "FixtureId": 66,
          "PathId": 2,
          "ChannelStartOverride": -1
        },
        {
          "FixtureType": "PlantFixture",
          "FixtureId": 87,
          "PathId": 3,
          "ChannelStartOverride": -1
        },
        {
          "FixtureType": "PlantFixture",
          "FixtureId": 108,
          "PathId": 4,
          "ChannelStartOverride": -1
        },
        {
          "FixtureType": "PlantFixture",
          "FixtureId": 129,
          "PathId": 5,
          "ChannelStartOverride": -1
        },
        {
          "FixtureType": "PlantFixture",
          "FixtureId": 150,
          "PathId": 6,
          "ChannelStartOverride": -1
        }
      ]
    }
  ],
  "portals": [
    {
      "portalId": "Portal0",
      "x": 1260.00073,
      "z": 0.0,
      "rotation": {
        "rotX": 0.0,
        "rotY": 180.0,
        "rotZ": 0.0
      }
    },
    {
      "portalId": "Portal1",
      "x": -5.507638E-05,
      "z": 1260.00073,
      "rotation": {
        "rotX": 0.0,
        "rotY": 90.0,
        "rotZ": 0.0
      }
    },
    {
      "portalId": "Portal2",
      "x": -1260.00073,
      "z": -0.00011015276,
      "rotation": {
        "rotX": 0.0,
        "rotY": 0.0,
        "rotZ": 0.0
      }
    },
    {
      "portalId": "Portal3",
      "x": 1.50253582E-05,
      "z": -1260.00073,
      "rotation": {
        "rotX": 0.0,
        "rotY": 270.0,
        "rotZ": 0.0
      }
    }
  ],
  "booths": [
    {
      "boothId": "Booth0",
      "x": -1103.087,
      "z": 1103.087,
      "rotation": {
        "rotX": 0.0,
        "rotY": 0.0,
        "rotZ": 0.0
      }
    },
    {
      "boothId": "Booth1",
      "x": -1103.087,
      "z": 1103.087,
      "rotation": {
        "rotX": 0.0,
        "rotY": 0.0,
        "rotZ": 0.0
      }
    }
  ]
}